[
  {
    "SpeciesCode": "SI18-4",
    "Scientificname": "Cenococcum geophilum (coll.) sp.3",
    "Svampguiden": "0",
    "Kriteriedokumentation": null,
    "OVANLIGHET": null,
    "KALKmark": null,
    "ANNANmark": null,
    "Värdtaxa:Vedochbark": null,
    "Värdtaxa:Finarerötterochrottrådar": null,
    "ekologi": null,
    "Commonname": "jordgryn",
    "matsvamp": 0,
    "total_presence": 423,
    "Artfakta": "https://artfakta.se/artinformation/taxa/3222/detaljer",
    "RL2020kat": "NE",
    "Svamp-grupp": "övrigt",
    "Svamp-Undersvamp-grupp": "0",
    "SIGNAL_art": "0",
    "Nyasvamp-boken": "0",
    "Giftsvamp": "0",
    "Genus": "Cenococcum",
    "sample_plot_count": 5,
    "sample_env_count": 6,
    "Svamp-grupp-släkte": "övrigt",
    "images": []
  },
  {
    "SpeciesCode": "SI18-369",
    "Scientificname": "Lactarius necator",
    "Svampguiden": "0",
    "Kriteriedokumentation": "De skattade värdena som bedömningen baserar sig på ligger alla inom intervallet för kategorin Livskraftig (LC).",
    "OVANLIGHET": 1,
    "KALKmark": null,
    "ANNANmark": "y",
    "Värdtaxa:Vedochbark": null,
    "Värdtaxa:Finarerötterochrottrådar": "gran björk",
    "ekologi": null,
    "Commonname": "svartriska",
    "matsvamp": 0,
    "total_presence": 11,
    "Artfakta": "https://artfakta.se/artinformation/taxa/4747/detaljer",
    "RL2020kat": "LC",
    "Svamp-grupp": "hattsvamp",
    "Svamp-Undersvamp-grupp": "0",
    "SIGNAL_art": "0",
    "Nyasvamp-boken": "0",
    "Giftsvamp": "x",
    "Genus": "Lactarius",
    "sample_plot_count": 4,
    "sample_env_count": 6,
    "Svamp-grupp-släkte": "hattsvamp",
    "images": [
      "/images/SvampBilder/Giftsvampar/Lactarius necator-33-4747.jpg",
      "/images/SvampBilder/Giftsvampar/Lactarius necator-32-4747.jpg"
    ]
  },
  {
    "SpeciesCode": "SI18-10",
    "Scientificname": "Tylospora fibrillosa",
    "Svampguiden": "0",
    "Kriteriedokumentation": "De skattade värdena som bedömningen baserar sig på ligger alla inom intervallet för kategorin Livskraftig (LC).",
    "OVANLIGHET": null,
    "KALKmark": null,
    "ANNANmark": null,
    "Värdtaxa:Vedochbark": "Trivial deciduous forest trees - red list assemblage, Hardwood forest trees - red list assemblage, Conifers - red list assemblage, Biota",
    "Värdtaxa:Finarerötterochrottrådar": null,
    "ekologi": null,
    "Commonname": "bomullsskinn",
    "matsvamp": 0,
    "total_presence": 140,
    "Artfakta": "https://artfakta.se/artinformation/taxa/6347/detaljer",
    "RL2020kat": "LC",
    "Svamp-grupp": "skinnsvamp",
    "Svamp-Undersvamp-grupp": "0",
    "SIGNAL_art": "0",
    "Nyasvamp-boken": "0",
    "Giftsvamp": "0",
    "Genus": "Tylospora",
    "sample_plot_count": 3,
    "sample_env_count": 6,
    "Svamp-grupp-släkte": "skinnsvamp",
    "images": []
  },
  {
    "SpeciesCode": "SI18-101",
    "Scientificname": "Lactarius tabidus",
    "Svampguiden": "0",
    "Kriteriedokumentation": "De skattade värdena som bedömningen baserar sig på ligger alla inom intervallet för kategorin Livskraftig (LC).",
    "OVANLIGHET": null,
    "KALKmark": null,
    "ANNANmark": null,
    "Värdtaxa:Vedochbark": null,
    "Värdtaxa:Finarerötterochrottrådar": null,
    "ekologi": null,
    "Commonname": "småriska",
    "matsvamp": 0,
    "total_presence": 32,
    "Artfakta": "https://artfakta.se/artinformation/taxa/236531/detaljer",
    "RL2020kat": "LC",
    "Svamp-grupp": "hattsvamp",
    "Svamp-Undersvamp-grupp": "0",
    "SIGNAL_art": "0",
    "Nyasvamp-boken": "0",
    "Giftsvamp": "0",
    "Genus": "Lactarius",
    "sample_plot_count": 3,
    "sample_env_count": 6,
    "Svamp-grupp-släkte": "hattsvamp",
    "images": []
  },
  {
    "SpeciesCode": "SI18-24",
    "Scientificname": "Hyaloscypha variabilis",
    "Svampguiden": "0",
    "Kriteriedokumentation": null,
    "OVANLIGHET": null,
    "KALKmark": null,
    "ANNANmark": null,
    "Värdtaxa:Vedochbark": null,
    "Värdtaxa:Finarerötterochrottrådar": null,
    "ekologi": null,
    "Commonname": "disksvamp",
    "matsvamp": 0,
    "total_presence": 68,
    "Artfakta": "Information saknas",
    "RL2020kat": "0",
    "Svamp-grupp": "0",
    "Svamp-Undersvamp-grupp": "0",
    "SIGNAL_art": "0",
    "Nyasvamp-boken": "0",
    "Giftsvamp": "0",
    "Genus": "Hyaloscypha",
    "sample_plot_count": 3,
    "sample_env_count": 6,
    "Svamp-grupp-släkte": "skålsvamp",
    "images": []
  },
  {
    "SpeciesCode": "SI18-35",
    "Scientificname": "Tylospora asterophora",
    "Svampguiden": "0",
    "Kriteriedokumentation": "De skattade värdena som bedömningen baserar sig på ligger alla inom intervallet för kategorin Livskraftig (LC).",
    "OVANLIGHET": null,
    "KALKmark": null,
    "ANNANmark": null,
    "Värdtaxa:Vedochbark": "Trivial deciduous forest trees - red list assemblage, Hardwood forest trees - red list assemblage, Conifers - red list assemblage, Biota",
    "Värdtaxa:Finarerötterochrottrådar": null,
    "ekologi": null,
    "Commonname": "astralskinn",
    "matsvamp": 0,
    "total_presence": 134,
    "Artfakta": "https://artfakta.se/artinformation/taxa/6346/detaljer",
    "RL2020kat": "LC",
    "Svamp-grupp": "skinnsvamp",
    "Svamp-Undersvamp-grupp": "0",
    "SIGNAL_art": "0",
    "Nyasvamp-boken": "0",
    "Giftsvamp": "0",
    "Genus": "Tylospora",
    "sample_plot_count": 3,
    "sample_env_count": 6,
    "Svamp-grupp-släkte": "skinnsvamp",
    "images": []
  },
  {
    "SpeciesCode": "SI18-74",
    "Scientificname": "Amphinema byssoides sp.3",
    "Svampguiden": "0",
    "Kriteriedokumentation": "De skattade värdena som bedömningen baserar sig på ligger alla inom intervallet för kategorin Livskraftig (LC).",
    "OVANLIGHET": null,
    "KALKmark": null,
    "ANNANmark": null,
    "Värdtaxa:Vedochbark": "Betula, Alnus, Populus tremula, Pinus sylvestris, Picea abies",
    "Värdtaxa:Finarerötterochrottrådar": "Pinus sylvestris, Picea abies",
    "ekologi": null,
    "Commonname": "kraterskinn",
    "matsvamp": 0,
    "total_presence": 41,
    "Artfakta": "https://artfakta.se/artinformation/taxa/2991/detaljer",
    "RL2020kat": "LC",
    "Svamp-grupp": "skinnsvamp",
    "Svamp-Undersvamp-grupp": "0",
    "SIGNAL_art": "0",
    "Nyasvamp-boken": "0",
    "Giftsvamp": "0",
    "Genus": "Amphinema",
    "sample_plot_count": 3,
    "sample_env_count": 6,
    "Svamp-grupp-släkte": "skinnsvamp",
    "images": []
  },
  {
    "SpeciesCode": "SI18-15",
    "Scientificname": "Piloderma sphaerosporum",
    "Svampguiden": "0",
    "Kriteriedokumentation": "De skattade värdena som bedömningen baserar sig på ligger alla inom intervallet för kategorin Livskraftig (LC).",
    "OVANLIGHET": null,
    "KALKmark": null,
    "ANNANmark": null,
    "Värdtaxa:Vedochbark": "Biota",
    "Värdtaxa:Finarerötterochrottrådar": "Biota",
    "ekologi": null,
    "Commonname": "skinnsvamp",
    "matsvamp": 0,
    "total_presence": 14,
    "Artfakta": "https://artfakta.se/artinformation/taxa/253758/detaljer",
    "RL2020kat": "LC",
    "Svamp-grupp": "skinnsvamp",
    "Svamp-Undersvamp-grupp": "0",
    "SIGNAL_art": "0",
    "Nyasvamp-boken": "0",
    "Giftsvamp": "0",
    "Genus": "Piloderma",
    "sample_plot_count": 2,
    "sample_env_count": 6,
    "Svamp-grupp-släkte": "skinnsvamp",
    "images": []
  },
  {
    "SpeciesCode": "SI18-214",
    "Scientificname": "Russula emetica (coll.) - betularum",
    "Svampguiden": "0",
    "Kriteriedokumentation": null,
    "OVANLIGHET": null,
    "KALKmark": null,
    "ANNANmark": null,
    "Värdtaxa:Vedochbark": null,
    "Värdtaxa:Finarerötterochrottrådar": null,
    "ekologi": null,
    "Commonname": "giftkremla",
    "matsvamp": 0,
    "total_presence": 6,
    "Artfakta": "Information saknas",
    "RL2020kat": "0",
    "Svamp-grupp": "0",
    "Svamp-Undersvamp-grupp": "0",
    "SIGNAL_art": "0",
    "Nyasvamp-boken": "0",
    "Giftsvamp": "0",
    "Genus": "Russula",
    "sample_plot_count": 2,
    "sample_env_count": 6,
    "Svamp-grupp-släkte": "hattsvamp",
    "images": []
  },
  {
    "SpeciesCode": "SI18-223",
    "Scientificname": "Cortinarius comptulus",
    "Svampguiden": "0",
    "Kriteriedokumentation": "De skattade värdena som bedömningen baserar sig på ligger alla inom intervallet för kategorin Livskraftig (LC).",
    "OVANLIGHET": null,
    "KALKmark": null,
    "ANNANmark": null,
    "Värdtaxa:Vedochbark": null,
    "Värdtaxa:Finarerötterochrottrådar": "Picea abies, Biota",
    "ekologi": null,
    "Commonname": "rundsporig spindling",
    "matsvamp": 0,
    "total_presence": 10,
    "Artfakta": "https://artfakta.se/artinformation/taxa/3587/detaljer",
    "RL2020kat": "LC",
    "Svamp-grupp": "hattsvamp",
    "Svamp-Undersvamp-grupp": "0",
    "SIGNAL_art": "0",
    "Nyasvamp-boken": "0",
    "Giftsvamp": "0",
    "Genus": "Cortinarius",
    "sample_plot_count": 2,
    "sample_env_count": 6,
    "Svamp-grupp-släkte": "hattsvamp",
    "images": []
  },
  {
    "SpeciesCode": "SI18-318",
    "Scientificname": "Russula puellaris",
    "Svampguiden": "0",
    "Kriteriedokumentation": "De skattade värdena som bedömningen baserar sig på ligger alla inom intervallet för kategorin Livskraftig (LC).",
    "OVANLIGHET": null,
    "KALKmark": null,
    "ANNANmark": null,
    "Värdtaxa:Vedochbark": null,
    "Värdtaxa:Finarerötterochrottrådar": null,
    "ekologi": null,
    "Commonname": "sienakremla",
    "matsvamp": 0,
    "total_presence": 6,
    "Artfakta": "https://artfakta.se/artinformation/taxa/5918/detaljer",
    "RL2020kat": "LC",
    "Svamp-grupp": "hattsvamp",
    "Svamp-Undersvamp-grupp": "0",
    "SIGNAL_art": "0",
    "Nyasvamp-boken": "0",
    "Giftsvamp": "0",
    "Genus": "Russula",
    "sample_plot_count": 2,
    "sample_env_count": 6,
    "Svamp-grupp-släkte": "hattsvamp",
    "images": []
  },
  {
    "SpeciesCode": "SI18-33",
    "Scientificname": "Piloderma byssinum",
    "Svampguiden": "0",
    "Kriteriedokumentation": "De skattade värdena som bedömningen baserar sig på ligger alla inom intervallet för kategorin Livskraftig (LC).",
    "OVANLIGHET": null,
    "KALKmark": null,
    "ANNANmark": null,
    "Värdtaxa:Vedochbark": "Biota",
    "Värdtaxa:Finarerötterochrottrådar": "Biota",
    "ekologi": null,
    "Commonname": "ullskinn",
    "matsvamp": 0,
    "total_presence": 42,
    "Artfakta": "https://artfakta.se/artinformation/taxa/5545/detaljer",
    "RL2020kat": "LC",
    "Svamp-grupp": "skinnsvamp",
    "Svamp-Undersvamp-grupp": "0",
    "SIGNAL_art": "0",
    "Nyasvamp-boken": "0",
    "Giftsvamp": "0",
    "Genus": "Piloderma",
    "sample_plot_count": 2,
    "sample_env_count": 6,
    "Svamp-grupp-släkte": "skinnsvamp",
    "images": []
  },
  {
    "SpeciesCode": "SI18-335",
    "Scientificname": "Trichophaea sp.4",
    "Svampguiden": "0",
    "Kriteriedokumentation": null,
    "OVANLIGHET": null,
    "KALKmark": null,
    "ANNANmark": null,
    "Värdtaxa:Vedochbark": null,
    "Värdtaxa:Finarerötterochrottrådar": null,
    "ekologi": null,
    "Commonname": "skålsvamp",
    "matsvamp": 0,
    "total_presence": 258,
    "Artfakta": "Information saknas",
    "RL2020kat": "0",
    "Svamp-grupp": "0",
    "Svamp-Undersvamp-grupp": "0",
    "SIGNAL_art": "0",
    "Nyasvamp-boken": "0",
    "Giftsvamp": "0",
    "Genus": "Trichophaea",
    "sample_plot_count": 2,
    "sample_env_count": 6,
    "Svamp-grupp-släkte": "skålsvamp",
    "images": []
  },
  {
    "SpeciesCode": "SI18-349",
    "Scientificname": "Hysterangium sp.1",
    "Svampguiden": "0",
    "Kriteriedokumentation": null,
    "OVANLIGHET": null,
    "KALKmark": null,
    "ANNANmark": null,
    "Värdtaxa:Vedochbark": null,
    "Värdtaxa:Finarerötterochrottrådar": null,
    "ekologi": null,
    "Commonname": "brosktryfflel",
    "matsvamp": 0,
    "total_presence": 4,
    "Artfakta": "Information saknas",
    "RL2020kat": "0",
    "Svamp-grupp": "0",
    "Svamp-Undersvamp-grupp": "0",
    "SIGNAL_art": "0",
    "Nyasvamp-boken": "0",
    "Giftsvamp": "0",
    "Genus": "Hysterangium",
    "sample_plot_count": 2,
    "sample_env_count": 6,
    "Svamp-grupp-släkte": "tryffel",
    "images": []
  },
  {
    "SpeciesCode": "SI18-520",
    "Scientificname": "Cortinarius casimiri",
    "Svampguiden": "0",
    "Kriteriedokumentation": "De skattade värdena som bedömningen baserar sig på ligger alla inom intervallet för kategorin Livskraftig (LC).",
    "OVANLIGHET": null,
    "KALKmark": null,
    "ANNANmark": null,
    "Värdtaxa:Vedochbark": "Biota",
    "Värdtaxa:Finarerötterochrottrådar": "Trivial deciduous forest trees - red list assemblage, Hardwood forest trees - red list assemblage, Conifers - red list assemblage, Biota",
    "ekologi": null,
    "Commonname": "storsporig spindling",
    "matsvamp": 0,
    "total_presence": 3,
    "Artfakta": "https://artfakta.se/artinformation/taxa/3577/detaljer",
    "RL2020kat": "LC",
    "Svamp-grupp": "hattsvamp",
    "Svamp-Undersvamp-grupp": "0",
    "SIGNAL_art": "0",
    "Nyasvamp-boken": "0",
    "Giftsvamp": "0",
    "Genus": "Cortinarius",
    "sample_plot_count": 2,
    "sample_env_count": 6,
    "Svamp-grupp-släkte": "hattsvamp",
    "images": []
  },
  {
    "SpeciesCode": "SI18-58",
    "Scientificname": "Piloderma olivaceum sp.2",
    "Svampguiden": "0",
    "Kriteriedokumentation": "De skattade värdena som bedömningen baserar sig på ligger alla inom intervallet för kategorin Livskraftig (LC).",
    "OVANLIGHET": null,
    "KALKmark": null,
    "ANNANmark": null,
    "Värdtaxa:Vedochbark": "Biota",
    "Värdtaxa:Finarerötterochrottrådar": "Biota",
    "ekologi": null,
    "Commonname": "mörkt ullskinn",
    "matsvamp": 0,
    "total_presence": 45,
    "Artfakta": "https://artfakta.se/artinformation/taxa/5548/detaljer",
    "RL2020kat": "LC",
    "Svamp-grupp": "skinnsvamp",
    "Svamp-Undersvamp-grupp": "0",
    "SIGNAL_art": "0",
    "Nyasvamp-boken": "0",
    "Giftsvamp": "0",
    "Genus": "Piloderma",
    "sample_plot_count": 2,
    "sample_env_count": 6,
    "Svamp-grupp-släkte": "skinnsvamp",
    "images": []
  },
  {
    "SpeciesCode": "SI18-85",
    "Scientificname": "Amanita fulva",
    "Svampguiden": "0",
    "Kriteriedokumentation": "De skattade värdena som bedömningen baserar sig på ligger alla inom intervallet för kategorin Livskraftig (LC).",
    "OVANLIGHET": null,
    "KALKmark": null,
    "ANNANmark": null,
    "Värdtaxa:Vedochbark": null,
    "Värdtaxa:Finarerötterochrottrådar": null,
    "ekologi": null,
    "Commonname": "brun kamskivling",
    "matsvamp": 0,
    "total_presence": 68,
    "Artfakta": "https://artfakta.se/artinformation/taxa/2974/detaljer",
    "RL2020kat": "LC",
    "Svamp-grupp": "hattsvamp",
    "Svamp-Undersvamp-grupp": "0",
    "SIGNAL_art": "0",
    "Nyasvamp-boken": "0",
    "Giftsvamp": "0",
    "Genus": "Amanita",
    "sample_plot_count": 2,
    "sample_env_count": 6,
    "Svamp-grupp-släkte": "hattsvamp",
    "images": []
  },
  {
    "SpeciesCode": "SI18-89",
    "Scientificname": "Atheliaceae sp.3",
    "Svampguiden": "0",
    "Kriteriedokumentation": null,
    "OVANLIGHET": null,
    "KALKmark": null,
    "ANNANmark": null,
    "Värdtaxa:Vedochbark": null,
    "Värdtaxa:Finarerötterochrottrådar": null,
    "ekologi": null,
    "Commonname": "skinnsvamp",
    "matsvamp": 0,
    "total_presence": 714,
    "Artfakta": "Information saknas",
    "RL2020kat": "0",
    "Svamp-grupp": "0",
    "Svamp-Undersvamp-grupp": "0",
    "SIGNAL_art": "0",
    "Nyasvamp-boken": "0",
    "Giftsvamp": "0",
    "Genus": "Information saknas",
    "sample_plot_count": 2,
    "sample_env_count": 6,
    "Svamp-grupp-släkte": "skinnsvamp",
    "images": []
  },
  {
    "SpeciesCode": "SI21-4212",
    "Scientificname": "Inocybe stellatospora",
    "Svampguiden": "0",
    "Kriteriedokumentation": "De skattade värdena som bedömningen baserar sig på ligger alla inom intervallet för kategorin Livskraftig (LC).",
    "OVANLIGHET": null,
    "KALKmark": null,
    "ANNANmark": null,
    "Värdtaxa:Vedochbark": null,
    "Värdtaxa:Finarerötterochrottrådar": "Pinus sylvestris, Picea abies, Fagus sylvatica",
    "ekologi": null,
    "Commonname": "trådskivling",
    "matsvamp": 0,
    "total_presence": 4,
    "Artfakta": "https://artfakta.se/artinformation/taxa/236458/detaljer",
    "RL2020kat": "LC",
    "Svamp-grupp": "hattsvamp",
    "Svamp-Undersvamp-grupp": "0",
    "SIGNAL_art": "0",
    "Nyasvamp-boken": "0",
    "Giftsvamp": "0",
    "Genus": "Inocybe",
    "sample_plot_count": 2,
    "sample_env_count": 6,
    "Svamp-grupp-släkte": "hattsvamp",
    "images": []
  },
  {
    "SpeciesCode": "SI18-1013",
    "Scientificname": "Phlegmacium glaucopus/subfoetens",
    "Svampguiden": "0",
    "Kriteriedokumentation": null,
    "OVANLIGHET": null,
    "KALKmark": null,
    "ANNANmark": null,
    "Värdtaxa:Vedochbark": null,
    "Värdtaxa:Finarerötterochrottrådar": null,
    "ekologi": null,
    "Commonname": "ädelspindling",
    "matsvamp": 0,
    "total_presence": 3,
    "Artfakta": "Information saknas",
    "RL2020kat": "0",
    "Svamp-grupp": "0",
    "Svamp-Undersvamp-grupp": "0",
    "SIGNAL_art": "0",
    "Nyasvamp-boken": "0",
    "Giftsvamp": "0",
    "Genus": "Phlegmacium",
    "sample_plot_count": 1,
    "sample_env_count": 6,
    "Svamp-grupp-släkte": "hattsvamp",
    "images": []
  },
  {
    "SpeciesCode": "SI18-1050",
    "Scientificname": "Sistotrema sp.1",
    "Svampguiden": "0",
    "Kriteriedokumentation": null,
    "OVANLIGHET": null,
    "KALKmark": null,
    "ANNANmark": null,
    "Värdtaxa:Vedochbark": null,
    "Värdtaxa:Finarerötterochrottrådar": null,
    "ekologi": null,
    "Commonname": "skinn/poring ",
    "matsvamp": 0,
    "total_presence": 28,
    "Artfakta": "Information saknas",
    "RL2020kat": "0",
    "Svamp-grupp": "0",
    "Svamp-Undersvamp-grupp": "0",
    "SIGNAL_art": "0",
    "Nyasvamp-boken": "0",
    "Giftsvamp": "0",
    "Genus": "Sistotrema",
    "sample_plot_count": 1,
    "sample_env_count": 6,
    "Svamp-grupp-släkte": "skinnsvamp",
    "images": []
  },
  {
    "SpeciesCode": "SI18-1072",
    "Scientificname": "Tylopilus felleus",
    "Svampguiden": "0",
    "Kriteriedokumentation": "De skattade värdena som bedömningen baserar sig på ligger alla inom intervallet för kategorin Livskraftig (LC).",
    "OVANLIGHET": null,
    "KALKmark": null,
    "ANNANmark": null,
    "Värdtaxa:Vedochbark": null,
    "Värdtaxa:Finarerötterochrottrådar": null,
    "ekologi": null,
    "Commonname": "gallsopp",
    "matsvamp": 0,
    "total_presence": 2,
    "Artfakta": "https://artfakta.se/artinformation/taxa/6345/detaljer",
    "RL2020kat": "LC",
    "Svamp-grupp": "sopp",
    "Svamp-Undersvamp-grupp": "0",
    "SIGNAL_art": "0",
    "Nyasvamp-boken": "0",
    "Giftsvamp": "0",
    "Genus": "Tylopilus",
    "sample_plot_count": 1,
    "sample_env_count": 6,
    "Svamp-grupp-släkte": "sopp",
    "images": []
  },
  {
    "SpeciesCode": "SI18-1126",
    "Scientificname": "Lactarius deterrimus/fennoscandicus",
    "Svampguiden": "0",
    "Kriteriedokumentation": null,
    "OVANLIGHET": null,
    "KALKmark": null,
    "ANNANmark": null,
    "Värdtaxa:Vedochbark": null,
    "Värdtaxa:Finarerötterochrottrådar": null,
    "ekologi": null,
    "Commonname": "granblodriska",
    "matsvamp": 0,
    "total_presence": 1,
    "Artfakta": "Information saknas",
    "RL2020kat": "0",
    "Svamp-grupp": "0",
    "Svamp-Undersvamp-grupp": "0",
    "SIGNAL_art": "0",
    "Nyasvamp-boken": "0",
    "Giftsvamp": "0",
    "Genus": "Lactarius",
    "sample_plot_count": 1,
    "sample_env_count": 6,
    "Svamp-grupp-släkte": "hattsvamp",
    "images": []
  },
  {
    "SpeciesCode": "SI18-127",
    "Scientificname": "Suillus bovinus",
    "Svampguiden": "https://svampguiden.com/art/visa/suillus_bovinus",
    "Kriteriedokumentation": "De skattade värdena som bedömningen baserar sig på ligger alla inom intervallet för kategorin Livskraftig (LC).",
    "OVANLIGHET": null,
    "KALKmark": null,
    "ANNANmark": "x",
    "Värdtaxa:Vedochbark": null,
    "Värdtaxa:Finarerötterochrottrådar": null,
    "ekologi": "Växer med tall på sandig mark längs skogsvägar och på tallhedar. Förekommer i stora grupper eller klungor.",
    "Commonname": "örsopp",
    "matsvamp": 1,
    "total_presence": 1,
    "Artfakta": "https://artfakta.se/artinformation/taxa/6084/detaljer",
    "RL2020kat": "LC",
    "Svamp-grupp": "sopp",
    "Svamp-Undersvamp-grupp": "0",
    "SIGNAL_art": "0",
    "Nyasvamp-boken": "x",
    "Giftsvamp": "0",
    "Genus": "Suillus",
    "sample_plot_count": 1,
    "sample_env_count": 6,
    "Svamp-grupp-släkte": "sopp",
    "images": [
      "/images/SvampBilder/Matsvampar/Suillus bovinus-5.jpg",
      "/images/SvampBilder/Matsvampar/Suillus bovinus-4.jpg",
      "/images/SvampBilder/Matsvampar/Suillus bovinus-6.jpg",
      "/images/SvampBilder/Matsvampar/Suillus bovinus-7.jpg",
      "/images/SvampBilder/Matsvampar/Suillus bovinus-3.jpg",
      "/images/SvampBilder/Matsvampar/Suillus bovinus-2.jpg",
      "/images/SvampBilder/Matsvampar/Suillus bovinus-1.jpg"
    ]
  },
  {
    "SpeciesCode": "SI18-136",
    "Scientificname": "Amphinema byssoides sp.1",
    "Svampguiden": "0",
    "Kriteriedokumentation": "De skattade värdena som bedömningen baserar sig på ligger alla inom intervallet för kategorin Livskraftig (LC).",
    "OVANLIGHET": null,
    "KALKmark": null,
    "ANNANmark": null,
    "Värdtaxa:Vedochbark": "Betula, Alnus, Populus tremula, Pinus sylvestris, Picea abies",
    "Värdtaxa:Finarerötterochrottrådar": "Pinus sylvestris, Picea abies",
    "ekologi": null,
    "Commonname": "kraterskinn",
    "matsvamp": 0,
    "total_presence": 2,
    "Artfakta": "https://artfakta.se/artinformation/taxa/2991/detaljer",
    "RL2020kat": "LC",
    "Svamp-grupp": "skinnsvamp",
    "Svamp-Undersvamp-grupp": "0",
    "SIGNAL_art": "0",
    "Nyasvamp-boken": "0",
    "Giftsvamp": "0",
    "Genus": "Amphinema",
    "sample_plot_count": 1,
    "sample_env_count": 6,
    "Svamp-grupp-släkte": "skinnsvamp",
    "images": []
  },
  {
    "SpeciesCode": "SI18-1428",
    "Scientificname": "Tuber anniae sp.1",
    "Svampguiden": "0",
    "Kriteriedokumentation": null,
    "OVANLIGHET": null,
    "KALKmark": null,
    "ANNANmark": null,
    "Värdtaxa:Vedochbark": null,
    "Värdtaxa:Finarerötterochrottrådar": null,
    "ekologi": null,
    "Commonname": "ädeltryffel",
    "matsvamp": 0,
    "total_presence": 2,
    "Artfakta": "Information saknas",
    "RL2020kat": "0",
    "Svamp-grupp": "0",
    "Svamp-Undersvamp-grupp": "0",
    "SIGNAL_art": "0",
    "Nyasvamp-boken": "0",
    "Giftsvamp": "0",
    "Genus": "Tuber",
    "sample_plot_count": 1,
    "sample_env_count": 6,
    "Svamp-grupp-släkte": "tryffel",
    "images": []
  },
  {
    "SpeciesCode": "SI18-143",
    "Scientificname": "Elaphomyces asperulus",
    "Svampguiden": "0",
    "Kriteriedokumentation": "De skattade värdena som bedömningen baserar sig på ligger alla inom intervallet för kategorin Livskraftig (LC).",
    "OVANLIGHET": null,
    "KALKmark": null,
    "ANNANmark": null,
    "Värdtaxa:Vedochbark": "Biota",
    "Värdtaxa:Finarerötterochrottrådar": null,
    "ekologi": null,
    "Commonname": "ljusbrun hjorttryffel",
    "matsvamp": 0,
    "total_presence": 18,
    "Artfakta": "https://artfakta.se/artinformation/taxa/3925/detaljer",
    "RL2020kat": "LC",
    "Svamp-grupp": "tryffel",
    "Svamp-Undersvamp-grupp": "0",
    "SIGNAL_art": "0",
    "Nyasvamp-boken": "0",
    "Giftsvamp": "0",
    "Genus": "Elaphomyces",
    "sample_plot_count": 1,
    "sample_env_count": 6,
    "Svamp-grupp-släkte": "tryffel",
    "images": []
  },
  {
    "SpeciesCode": "SI18-166",
    "Scientificname": "Piloderma sp.3",
    "Svampguiden": "0",
    "Kriteriedokumentation": null,
    "OVANLIGHET": null,
    "KALKmark": null,
    "ANNANmark": null,
    "Värdtaxa:Vedochbark": null,
    "Värdtaxa:Finarerötterochrottrådar": null,
    "ekologi": null,
    "Commonname": "skinnsvamp",
    "matsvamp": 0,
    "total_presence": 180,
    "Artfakta": "Information saknas",
    "RL2020kat": "0",
    "Svamp-grupp": "0",
    "Svamp-Undersvamp-grupp": "0",
    "SIGNAL_art": "0",
    "Nyasvamp-boken": "0",
    "Giftsvamp": "0",
    "Genus": "Piloderma",
    "sample_plot_count": 1,
    "sample_env_count": 6,
    "Svamp-grupp-släkte": "skinnsvamp",
    "images": []
  },
  {
    "SpeciesCode": "SI18-1745",
    "Scientificname": "Cortinarius causticus",
    "Svampguiden": "0",
    "Kriteriedokumentation": "De skattade värdena som bedömningen baserar sig på ligger alla inom intervallet för kategorin Livskraftig (LC).",
    "OVANLIGHET": null,
    "KALKmark": null,
    "ANNANmark": null,
    "Värdtaxa:Vedochbark": null,
    "Värdtaxa:Finarerötterochrottrådar": "Biota",
    "ekologi": null,
    "Commonname": "pepparspindling",
    "matsvamp": 0,
    "total_presence": 1,
    "Artfakta": "https://artfakta.se/artinformation/taxa/3579/detaljer",
    "RL2020kat": "LC",
    "Svamp-grupp": "hattsvamp",
    "Svamp-Undersvamp-grupp": "0",
    "SIGNAL_art": "0",
    "Nyasvamp-boken": "0",
    "Giftsvamp": "0",
    "Genus": "Cortinarius",
    "sample_plot_count": 1,
    "sample_env_count": 6,
    "Svamp-grupp-släkte": "hattsvamp",
    "images": []
  },
  {
    "SpeciesCode": "SI18-1918",
    "Scientificname": "Russula nigricans",
    "Svampguiden": "0",
    "Kriteriedokumentation": "De skattade värdena som bedömningen baserar sig på ligger alla inom intervallet för kategorin Livskraftig (LC).",
    "OVANLIGHET": null,
    "KALKmark": null,
    "ANNANmark": null,
    "Värdtaxa:Vedochbark": null,
    "Värdtaxa:Finarerötterochrottrådar": null,
    "ekologi": null,
    "Commonname": "svartkremla",
    "matsvamp": 0,
    "total_presence": 5,
    "Artfakta": "https://artfakta.se/artinformation/taxa/5898/detaljer",
    "RL2020kat": "LC",
    "Svamp-grupp": "hattsvamp",
    "Svamp-Undersvamp-grupp": "0",
    "SIGNAL_art": "0",
    "Nyasvamp-boken": "0",
    "Giftsvamp": "0",
    "Genus": "Russula",
    "sample_plot_count": 1,
    "sample_env_count": 6,
    "Svamp-grupp-släkte": "hattsvamp",
    "images": []
  },
  {
    "SpeciesCode": "SI18-192",
    "Scientificname": "Cortinarius brunneus",
    "Svampguiden": "0",
    "Kriteriedokumentation": "De skattade värdena som bedömningen baserar sig på ligger alla inom intervallet för kategorin Livskraftig (LC).",
    "OVANLIGHET": null,
    "KALKmark": null,
    "ANNANmark": null,
    "Värdtaxa:Vedochbark": null,
    "Värdtaxa:Finarerötterochrottrådar": null,
    "ekologi": null,
    "Commonname": "umbraspindling",
    "matsvamp": 0,
    "total_presence": 10,
    "Artfakta": "https://artfakta.se/artinformation/taxa/249286/detaljer",
    "RL2020kat": "LC",
    "Svamp-grupp": "hattsvamp",
    "Svamp-Undersvamp-grupp": "0",
    "SIGNAL_art": "0",
    "Nyasvamp-boken": "0",
    "Giftsvamp": "0",
    "Genus": "Cortinarius",
    "sample_plot_count": 1,
    "sample_env_count": 6,
    "Svamp-grupp-släkte": "hattsvamp",
    "images": []
  },
  {
    "SpeciesCode": "SI18-217",
    "Scientificname": "Polyozellus humicola",
    "Svampguiden": "0",
    "Kriteriedokumentation": null,
    "OVANLIGHET": null,
    "KALKmark": null,
    "ANNANmark": null,
    "Värdtaxa:Vedochbark": null,
    "Värdtaxa:Finarerötterochrottrådar": null,
    "ekologi": null,
    "Commonname": "tomentelloid svamp",
    "matsvamp": 0,
    "total_presence": 1,
    "Artfakta": "https://artfakta.se/artinformation/taxa/6046595/detaljer",
    "RL2020kat": "NE",
    "Svamp-grupp": "skinnsvamp",
    "Svamp-Undersvamp-grupp": "0",
    "SIGNAL_art": "0",
    "Nyasvamp-boken": "0",
    "Giftsvamp": "0",
    "Genus": "Polyozellus",
    "sample_plot_count": 1,
    "sample_env_count": 6,
    "Svamp-grupp-släkte": "skinnsvamp",
    "images": []
  },
  {
    "SpeciesCode": "SI18-2209",
    "Scientificname": "Inocybe mixtilis",
    "Svampguiden": "0",
    "Kriteriedokumentation": "De skattade värdena som bedömningen baserar sig på ligger alla inom intervallet för kategorin Livskraftig (LC).",
    "OVANLIGHET": null,
    "KALKmark": null,
    "ANNANmark": null,
    "Värdtaxa:Vedochbark": null,
    "Värdtaxa:Finarerötterochrottrådar": "Conifers - red list assemblage",
    "ekologi": null,
    "Commonname": "löktråding",
    "matsvamp": 0,
    "total_presence": 18,
    "Artfakta": "https://artfakta.se/artinformation/taxa/4612/detaljer",
    "RL2020kat": "LC",
    "Svamp-grupp": "hattsvamp",
    "Svamp-Undersvamp-grupp": "0",
    "SIGNAL_art": "0",
    "Nyasvamp-boken": "0",
    "Giftsvamp": "0",
    "Genus": "Inocybe",
    "sample_plot_count": 1,
    "sample_env_count": 6,
    "Svamp-grupp-släkte": "hattsvamp",
    "images": []
  },
  {
    "SpeciesCode": "SI18-256",
    "Scientificname": "Russula velenovskyi",
    "Svampguiden": "0",
    "Kriteriedokumentation": "De skattade värdena som bedömningen baserar sig på ligger alla inom intervallet för kategorin Livskraftig (LC).",
    "OVANLIGHET": null,
    "KALKmark": null,
    "ANNANmark": "x",
    "Värdtaxa:Vedochbark": null,
    "Värdtaxa:Finarerötterochrottrådar": null,
    "ekologi": null,
    "Commonname": "gulröd kremla",
    "matsvamp": 1,
    "total_presence": 11,
    "Artfakta": "https://artfakta.se/artinformation/taxa/5940/detaljer",
    "RL2020kat": "LC",
    "Svamp-grupp": "hattsvamp",
    "Svamp-Undersvamp-grupp": "0",
    "SIGNAL_art": "0",
    "Nyasvamp-boken": "x",
    "Giftsvamp": "0",
    "Genus": "Russula",
    "sample_plot_count": 1,
    "sample_env_count": 6,
    "Svamp-grupp-släkte": "hattsvamp",
    "images": []
  },
  {
    "SpeciesCode": "SI18-26",
    "Scientificname": "Hyaloscypha finlandica sp.1",
    "Svampguiden": "0",
    "Kriteriedokumentation": null,
    "OVANLIGHET": null,
    "KALKmark": null,
    "ANNANmark": null,
    "Värdtaxa:Vedochbark": null,
    "Värdtaxa:Finarerötterochrottrådar": null,
    "ekologi": null,
    "Commonname": "disksvamp",
    "matsvamp": 0,
    "total_presence": 8,
    "Artfakta": "Information saknas",
    "RL2020kat": "0",
    "Svamp-grupp": "0",
    "Svamp-Undersvamp-grupp": "0",
    "SIGNAL_art": "0",
    "Nyasvamp-boken": "0",
    "Giftsvamp": "0",
    "Genus": "Hyaloscypha",
    "sample_plot_count": 1,
    "sample_env_count": 6,
    "Svamp-grupp-släkte": "skålsvamp",
    "images": []
  },
  {
    "SpeciesCode": "SI18-28",
    "Scientificname": "Russula decolorans",
    "Svampguiden": "https://svampguiden.com/art/visa/russula_decolorans",
    "Kriteriedokumentation": "De skattade värdena som bedömningen baserar sig på ligger alla inom intervallet för kategorin Livskraftig (LC).",
    "OVANLIGHET": null,
    "KALKmark": null,
    "ANNANmark": "x",
    "Värdtaxa:Vedochbark": null,
    "Värdtaxa:Finarerötterochrottrådar": null,
    "ekologi": "Växer i barrskog över hela Sverige, vanlig i lavrik mager tallskog.",
    "Commonname": "tegelkremla",
    "matsvamp": 1,
    "total_presence": 7,
    "Artfakta": "https://artfakta.se/artinformation/taxa/5852/detaljer",
    "RL2020kat": "LC",
    "Svamp-grupp": "hattsvamp",
    "Svamp-Undersvamp-grupp": "0",
    "SIGNAL_art": "0",
    "Nyasvamp-boken": "x",
    "Giftsvamp": "0",
    "Genus": "Russula",
    "sample_plot_count": 1,
    "sample_env_count": 6,
    "Svamp-grupp-släkte": "hattsvamp",
    "images": [
      "/images/SvampBilder/Matsvampar/Russula decolorans-4.jpg",
      "/images/SvampBilder/Matsvampar/Russula decolorans-1.jpg",
      "/images/SvampBilder/Matsvampar/Russula decolorans-2.jpg",
      "/images/SvampBilder/Matsvampar/Russula decolorans-3.jpg"
    ]
  },
  {
    "SpeciesCode": "SI18-306",
    "Scientificname": "Piloderma sp.9",
    "Svampguiden": "0",
    "Kriteriedokumentation": null,
    "OVANLIGHET": null,
    "KALKmark": null,
    "ANNANmark": null,
    "Värdtaxa:Vedochbark": null,
    "Värdtaxa:Finarerötterochrottrådar": null,
    "ekologi": null,
    "Commonname": "skinnsvamp",
    "matsvamp": 0,
    "total_presence": 380,
    "Artfakta": "Information saknas",
    "RL2020kat": "0",
    "Svamp-grupp": "0",
    "Svamp-Undersvamp-grupp": "0",
    "SIGNAL_art": "0",
    "Nyasvamp-boken": "0",
    "Giftsvamp": "0",
    "Genus": "Piloderma",
    "sample_plot_count": 1,
    "sample_env_count": 6,
    "Svamp-grupp-släkte": "skinnsvamp",
    "images": []
  },
  {
    "SpeciesCode": "SI18-31",
    "Scientificname": "Piloderma olivaceum sp.1",
    "Svampguiden": "0",
    "Kriteriedokumentation": "De skattade värdena som bedömningen baserar sig på ligger alla inom intervallet för kategorin Livskraftig (LC).",
    "OVANLIGHET": null,
    "KALKmark": null,
    "ANNANmark": null,
    "Värdtaxa:Vedochbark": "Biota",
    "Värdtaxa:Finarerötterochrottrådar": "Biota",
    "ekologi": null,
    "Commonname": "mörkt ullskinn",
    "matsvamp": 0,
    "total_presence": 3,
    "Artfakta": "https://artfakta.se/artinformation/taxa/5548/detaljer",
    "RL2020kat": "LC",
    "Svamp-grupp": "skinnsvamp",
    "Svamp-Undersvamp-grupp": "0",
    "SIGNAL_art": "0",
    "Nyasvamp-boken": "0",
    "Giftsvamp": "0",
    "Genus": "Piloderma",
    "sample_plot_count": 1,
    "sample_env_count": 6,
    "Svamp-grupp-släkte": "skinnsvamp",
    "images": []
  },
  {
    "SpeciesCode": "SI18-320",
    "Scientificname": "Tomentella badia sp.2",
    "Svampguiden": "0",
    "Kriteriedokumentation": "Svensk förekomst: Bofast och reproducerande, Svensk invandringshistoria: Spontan.",
    "OVANLIGHET": null,
    "KALKmark": null,
    "ANNANmark": null,
    "Värdtaxa:Vedochbark": "Biota",
    "Värdtaxa:Finarerötterochrottrådar": "Biota",
    "ekologi": null,
    "Commonname": "tomentelloid svamp",
    "matsvamp": 0,
    "total_presence": 22,
    "Artfakta": "https://artfakta.se/artinformation/taxa/6159/detaljer",
    "RL2020kat": "NA",
    "Svamp-grupp": "skinnsvamp",
    "Svamp-Undersvamp-grupp": "0",
    "SIGNAL_art": "0",
    "Nyasvamp-boken": "0",
    "Giftsvamp": "0",
    "Genus": "Tomentella",
    "sample_plot_count": 1,
    "sample_env_count": 6,
    "Svamp-grupp-släkte": "skinnsvamp",
    "images": []
  },
  {
    "SpeciesCode": "SI18-3391",
    "Scientificname": "Byssocorticium pulchrum",
    "Svampguiden": "0",
    "Kriteriedokumentation": "De skattade värdena som bedömningen baserar sig på ligger alla inom intervallet för kategorin Livskraftig (LC).",
    "OVANLIGHET": null,
    "KALKmark": null,
    "ANNANmark": null,
    "Värdtaxa:Vedochbark": "Conifers - red list assemblage, Populus, Pinus, Quercus, Picea, Fagus, Betula, Alnus",
    "Värdtaxa:Finarerötterochrottrådar": null,
    "ekologi": null,
    "Commonname": "ärgskinn",
    "matsvamp": 0,
    "total_presence": 3,
    "Artfakta": "https://artfakta.se/artinformation/taxa/3176/detaljer",
    "RL2020kat": "LC",
    "Svamp-grupp": "skinnsvamp",
    "Svamp-Undersvamp-grupp": "0",
    "SIGNAL_art": "0",
    "Nyasvamp-boken": "0",
    "Giftsvamp": "0",
    "Genus": "Byssocorticium",
    "sample_plot_count": 1,
    "sample_env_count": 6,
    "Svamp-grupp-släkte": "skinnsvamp",
    "images": []
  },
  {
    "SpeciesCode": "SI18-386",
    "Scientificname": "Hydnotrya tulasnei",
    "Svampguiden": "0",
    "Kriteriedokumentation": null,
    "OVANLIGHET": null,
    "KALKmark": null,
    "ANNANmark": null,
    "Värdtaxa:Vedochbark": null,
    "Värdtaxa:Finarerötterochrottrådar": "Trivial deciduous forest trees - red list assemblage, Conifers - red list assemblage",
    "ekologi": null,
    "Commonname": "vecktryffel",
    "matsvamp": 0,
    "total_presence": 3,
    "Artfakta": "https://artfakta.se/artinformation/taxa/4369/detaljer",
    "RL2020kat": "NE",
    "Svamp-grupp": "tryffel",
    "Svamp-Undersvamp-grupp": "0",
    "SIGNAL_art": "0",
    "Nyasvamp-boken": "0",
    "Giftsvamp": "0",
    "Genus": "Hydnotrya",
    "sample_plot_count": 1,
    "sample_env_count": 6,
    "Svamp-grupp-släkte": "tryffel",
    "images": []
  },
  {
    "SpeciesCode": "SI18-411",
    "Scientificname": "Elaphomyces granulatus",
    "Svampguiden": "0",
    "Kriteriedokumentation": "De skattade värdena som bedömningen baserar sig på ligger alla inom intervallet för kategorin Livskraftig (LC).",
    "OVANLIGHET": null,
    "KALKmark": null,
    "ANNANmark": null,
    "Värdtaxa:Vedochbark": "Biota",
    "Värdtaxa:Finarerötterochrottrådar": null,
    "ekologi": null,
    "Commonname": "grynig hjorttryffel",
    "matsvamp": 0,
    "total_presence": 6,
    "Artfakta": "https://artfakta.se/artinformation/taxa/3926/detaljer",
    "RL2020kat": "LC",
    "Svamp-grupp": "tryffel",
    "Svamp-Undersvamp-grupp": "0",
    "SIGNAL_art": "0",
    "Nyasvamp-boken": "0",
    "Giftsvamp": "0",
    "Genus": "Elaphomyces",
    "sample_plot_count": 1,
    "sample_env_count": 6,
    "Svamp-grupp-släkte": "tryffel",
    "images": []
  },
  {
    "SpeciesCode": "SI18-416",
    "Scientificname": "Lactarius camphoratus",
    "Svampguiden": "0",
    "Kriteriedokumentation": "De skattade värdena som bedömningen baserar sig på ligger alla inom intervallet för kategorin Livskraftig (LC).",
    "OVANLIGHET": null,
    "KALKmark": null,
    "ANNANmark": null,
    "Värdtaxa:Vedochbark": null,
    "Värdtaxa:Finarerötterochrottrådar": null,
    "ekologi": null,
    "Commonname": "kamferriska",
    "matsvamp": 0,
    "total_presence": 4,
    "Artfakta": "https://artfakta.se/artinformation/taxa/4718/detaljer",
    "RL2020kat": "LC",
    "Svamp-grupp": "hattsvamp",
    "Svamp-Undersvamp-grupp": "0",
    "SIGNAL_art": "0",
    "Nyasvamp-boken": "0",
    "Giftsvamp": "0",
    "Genus": "Lactarius",
    "sample_plot_count": 1,
    "sample_env_count": 6,
    "Svamp-grupp-släkte": "hattsvamp",
    "images": []
  },
  {
    "SpeciesCode": "SI18-418",
    "Scientificname": "Hyaloscypha finlandica sp.2",
    "Svampguiden": "0",
    "Kriteriedokumentation": null,
    "OVANLIGHET": null,
    "KALKmark": null,
    "ANNANmark": null,
    "Värdtaxa:Vedochbark": null,
    "Värdtaxa:Finarerötterochrottrådar": null,
    "ekologi": null,
    "Commonname": "disksvamp",
    "matsvamp": 0,
    "total_presence": 8,
    "Artfakta": "Information saknas",
    "RL2020kat": "0",
    "Svamp-grupp": "0",
    "Svamp-Undersvamp-grupp": "0",
    "SIGNAL_art": "0",
    "Nyasvamp-boken": "0",
    "Giftsvamp": "0",
    "Genus": "Hyaloscypha",
    "sample_plot_count": 1,
    "sample_env_count": 6,
    "Svamp-grupp-släkte": "skålsvamp",
    "images": []
  },
  {
    "SpeciesCode": "SI18-431",
    "Scientificname": "Hygrophorus pustulatus",
    "Svampguiden": "0",
    "Kriteriedokumentation": "De skattade värdena som bedömningen baserar sig på ligger alla inom intervallet för kategorin Livskraftig (LC).",
    "OVANLIGHET": null,
    "KALKmark": null,
    "ANNANmark": null,
    "Värdtaxa:Vedochbark": null,
    "Värdtaxa:Finarerötterochrottrådar": "Picea abies",
    "ekologi": null,
    "Commonname": "grynvaxskivling",
    "matsvamp": 0,
    "total_presence": 4,
    "Artfakta": "https://artfakta.se/artinformation/taxa/4423/detaljer",
    "RL2020kat": "LC",
    "Svamp-grupp": "hattsvamp",
    "Svamp-Undersvamp-grupp": "0",
    "SIGNAL_art": "0",
    "Nyasvamp-boken": "0",
    "Giftsvamp": "0",
    "Genus": "Hygrophorus",
    "sample_plot_count": 1,
    "sample_env_count": 6,
    "Svamp-grupp-släkte": "hattsvamp",
    "images": []
  },
  {
    "SpeciesCode": "SI18-4610",
    "Scientificname": "Helvellosebacina helvelloides (coll.) sp.1",
    "Svampguiden": "0",
    "Kriteriedokumentation": null,
    "OVANLIGHET": null,
    "KALKmark": null,
    "ANNANmark": null,
    "Värdtaxa:Vedochbark": null,
    "Värdtaxa:Finarerötterochrottrådar": null,
    "ekologi": null,
    "Commonname": "basidiesvamp",
    "matsvamp": 0,
    "total_presence": 10,
    "Artfakta": "Information saknas",
    "RL2020kat": "0",
    "Svamp-grupp": "0",
    "Svamp-Undersvamp-grupp": "0",
    "SIGNAL_art": "0",
    "Nyasvamp-boken": "0",
    "Giftsvamp": "0",
    "Genus": "Helvellosebacina",
    "sample_plot_count": 1,
    "sample_env_count": 6,
    "Svamp-grupp-släkte": "övrigt",
    "images": []
  },
  {
    "SpeciesCode": "SI18-475",
    "Scientificname": "Otidea leporina",
    "Svampguiden": "0",
    "Kriteriedokumentation": "De skattade värdena som bedömningen baserar sig på ligger alla inom intervallet för kategorin Livskraftig (LC).",
    "OVANLIGHET": null,
    "KALKmark": null,
    "ANNANmark": null,
    "Värdtaxa:Vedochbark": null,
    "Värdtaxa:Finarerötterochrottrådar": null,
    "ekologi": null,
    "Commonname": "litet haröra",
    "matsvamp": 0,
    "total_presence": 15,
    "Artfakta": "https://artfakta.se/artinformation/taxa/5313/detaljer",
    "RL2020kat": "LC",
    "Svamp-grupp": "skålsvamp",
    "Svamp-Undersvamp-grupp": "0",
    "SIGNAL_art": "0",
    "Nyasvamp-boken": "0",
    "Giftsvamp": "0",
    "Genus": "Otidea",
    "sample_plot_count": 1,
    "sample_env_count": 6,
    "Svamp-grupp-släkte": "skålsvamp",
    "images": []
  },
  {
    "SpeciesCode": "SI18-49",
    "Scientificname": "Piloderma bicolor",
    "Svampguiden": "0",
    "Kriteriedokumentation": null,
    "OVANLIGHET": null,
    "KALKmark": null,
    "ANNANmark": null,
    "Värdtaxa:Vedochbark": null,
    "Värdtaxa:Finarerötterochrottrådar": null,
    "ekologi": null,
    "Commonname": "gultrådsskinn",
    "matsvamp": 0,
    "total_presence": 1,
    "Artfakta": "Information saknas",
    "RL2020kat": "0",
    "Svamp-grupp": "0",
    "Svamp-Undersvamp-grupp": "0",
    "SIGNAL_art": "0",
    "Nyasvamp-boken": "0",
    "Giftsvamp": "0",
    "Genus": "Piloderma",
    "sample_plot_count": 1,
    "sample_env_count": 6,
    "Svamp-grupp-släkte": "skinnsvamp",
    "images": []
  },
  {
    "SpeciesCode": "SI18-493",
    "Scientificname": "Gautieria cf otthii",
    "Svampguiden": "0",
    "Kriteriedokumentation": null,
    "OVANLIGHET": null,
    "KALKmark": null,
    "ANNANmark": null,
    "Värdtaxa:Vedochbark": null,
    "Värdtaxa:Finarerötterochrottrådar": null,
    "ekologi": null,
    "Commonname": "håltryffel",
    "matsvamp": 0,
    "total_presence": 1,
    "Artfakta": "Information saknas",
    "RL2020kat": "0",
    "Svamp-grupp": "0",
    "Svamp-Undersvamp-grupp": "0",
    "SIGNAL_art": "0",
    "Nyasvamp-boken": "0",
    "Giftsvamp": "0",
    "Genus": "Gautieria",
    "sample_plot_count": 1,
    "sample_env_count": 6,
    "Svamp-grupp-släkte": "tryffel",
    "images": []
  },
  {
    "SpeciesCode": "SI18-529",
    "Scientificname": "Paxillus involutus",
    "Svampguiden": "0",
    "Kriteriedokumentation": null,
    "OVANLIGHET": 1,
    "KALKmark": null,
    "ANNANmark": "y",
    "Värdtaxa:Vedochbark": null,
    "Värdtaxa:Finarerötterochrottrådar": "Trivial deciduous forest trees - red list assemblage, Hardwood forest trees - red list assemblage, Conifers - red list assemblage",
    "ekologi": null,
    "Commonname": "pluggskivling",
    "matsvamp": 0,
    "total_presence": 3,
    "Artfakta": "https://artfakta.se/artinformation/taxa/6051059/detaljer",
    "RL2020kat": "0",
    "Svamp-grupp": "hattsvamp",
    "Svamp-Undersvamp-grupp": "0",
    "SIGNAL_art": "0",
    "Nyasvamp-boken": "0",
    "Giftsvamp": "x",
    "Genus": "Paxillus",
    "sample_plot_count": 1,
    "sample_env_count": 6,
    "Svamp-grupp-släkte": "hattsvamp",
    "images": [
      "/images/SvampBilder/Giftsvampar/Paxillus involutus-104-5351.jpg",
      "/images/SvampBilder/Giftsvampar/Paxillus involutus-98-5351.jpg"
    ]
  },
  {
    "SpeciesCode": "SI18-544",
    "Scientificname": "Cortinarius lucorum",
    "Svampguiden": "0",
    "Kriteriedokumentation": "De skattade värdena som bedömningen baserar sig på ligger alla inom intervallet för kategorin Livskraftig (LC).",
    "OVANLIGHET": null,
    "KALKmark": null,
    "ANNANmark": null,
    "Värdtaxa:Vedochbark": "Biota",
    "Värdtaxa:Finarerötterochrottrådar": "Biota",
    "ekologi": null,
    "Commonname": "aspspindling",
    "matsvamp": 0,
    "total_presence": 1,
    "Artfakta": "https://artfakta.se/artinformation/taxa/3656/detaljer",
    "RL2020kat": "LC",
    "Svamp-grupp": "hattsvamp",
    "Svamp-Undersvamp-grupp": "0",
    "SIGNAL_art": "0",
    "Nyasvamp-boken": "0",
    "Giftsvamp": "0",
    "Genus": "Cortinarius",
    "sample_plot_count": 1,
    "sample_env_count": 6,
    "Svamp-grupp-släkte": "hattsvamp",
    "images": []
  },
  {
    "SpeciesCode": "SI18-569",
    "Scientificname": "Polyozellus tristis",
    "Svampguiden": "0",
    "Kriteriedokumentation": "Taxonomiska utredningar har visat att den art som tidigare benämnts Pseudotomentella tristis egentligen är flera olika arter. Av egentliga P. tristis finns få fynd gjorda och de från de nordiska länderna är från gamla skogar på intermediör till rik mark. Spridd över Europa men fortfarande råder taxonomiska oklarheter. Faktaunderlaget bedöms vara otillräckligt för att avgöra vilken av de olika rödlistningskategorierna som är mest trolig.",
    "OVANLIGHET": 2,
    "KALKmark": null,
    "ANNANmark": "y",
    "Värdtaxa:Vedochbark": null,
    "Värdtaxa:Finarerötterochrottrådar": "Betula, Fagus sylvatica, Biota",
    "ekologi": null,
    "Commonname": "tomentelloid svamp",
    "matsvamp": 0,
    "total_presence": 1,
    "Artfakta": "https://artfakta.se/artinformation/taxa/6040135/detaljer",
    "RL2020kat": "DD",
    "Svamp-grupp": "skinnsvamp",
    "Svamp-Undersvamp-grupp": "0",
    "SIGNAL_art": "0",
    "Nyasvamp-boken": "0",
    "Giftsvamp": "0",
    "Genus": "Polyozellus",
    "sample_plot_count": 1,
    "sample_env_count": 6,
    "Svamp-grupp-släkte": "skinnsvamp",
    "images": []
  },
  {
    "SpeciesCode": "SI18-583",
    "Scientificname": "Boletus edulis sp.1",
    "Svampguiden": "https://svampguiden.com/art/visa/boletus_edulis",
    "Kriteriedokumentation": "De skattade värdena som bedömningen baserar sig på ligger alla inom intervallet för kategorin Livskraftig (LC).",
    "OVANLIGHET": null,
    "KALKmark": null,
    "ANNANmark": "x",
    "Värdtaxa:Vedochbark": null,
    "Värdtaxa:Finarerötterochrottrådar": null,
    "ekologi": "Växer i barr- och lövskog över hela Europa. Vissa år uppträder den i stora mängder under s.k. karljohanår. ",
    "Commonname": "stensopp",
    "matsvamp": 1,
    "total_presence": 6,
    "Artfakta": "https://artfakta.se/artinformation/taxa/245630/detaljer",
    "RL2020kat": "LC",
    "Svamp-grupp": "sopp",
    "Svamp-Undersvamp-grupp": "0",
    "SIGNAL_art": "0",
    "Nyasvamp-boken": "x",
    "Giftsvamp": "0",
    "Genus": "Boletus",
    "sample_plot_count": 1,
    "sample_env_count": 6,
    "Svamp-grupp-släkte": "sopp",
    "images": []
  },
  {
    "SpeciesCode": "SI18-593",
    "Scientificname": "Cortinarius sp.8",
    "Svampguiden": "0",
    "Kriteriedokumentation": null,
    "OVANLIGHET": null,
    "KALKmark": null,
    "ANNANmark": null,
    "Värdtaxa:Vedochbark": null,
    "Värdtaxa:Finarerötterochrottrådar": null,
    "ekologi": null,
    "Commonname": "spindelskivling",
    "matsvamp": 0,
    "total_presence": 80,
    "Artfakta": "Information saknas",
    "RL2020kat": "0",
    "Svamp-grupp": "0",
    "Svamp-Undersvamp-grupp": "0",
    "SIGNAL_art": "0",
    "Nyasvamp-boken": "0",
    "Giftsvamp": "0",
    "Genus": "Cortinarius",
    "sample_plot_count": 1,
    "sample_env_count": 6,
    "Svamp-grupp-släkte": "hattsvamp",
    "images": []
  },
  {
    "SpeciesCode": "SI18-6269",
    "Scientificname": "Cortinarius anomalus",
    "Svampguiden": "0",
    "Kriteriedokumentation": "De skattade värdena som bedömningen baserar sig på ligger alla inom intervallet för kategorin Livskraftig (LC).",
    "OVANLIGHET": null,
    "KALKmark": null,
    "ANNANmark": null,
    "Värdtaxa:Vedochbark": null,
    "Värdtaxa:Finarerötterochrottrådar": "Biota",
    "ekologi": null,
    "Commonname": "björkspindling",
    "matsvamp": 0,
    "total_presence": 2,
    "Artfakta": "https://artfakta.se/artinformation/taxa/3535/detaljer",
    "RL2020kat": "LC",
    "Svamp-grupp": "hattsvamp",
    "Svamp-Undersvamp-grupp": "0",
    "SIGNAL_art": "0",
    "Nyasvamp-boken": "0",
    "Giftsvamp": "0",
    "Genus": "Cortinarius",
    "sample_plot_count": 1,
    "sample_env_count": 6,
    "Svamp-grupp-släkte": "hattsvamp",
    "images": []
  },
  {
    "SpeciesCode": "SI18-669",
    "Scientificname": "Russula integra",
    "Svampguiden": "https://svampguiden.com/art/visa/russula_integra",
    "Kriteriedokumentation": "De skattade värdena som bedömningen baserar sig på ligger alla inom intervallet för kategorin Livskraftig (LC).",
    "OVANLIGHET": null,
    "KALKmark": null,
    "ANNANmark": "x",
    "Värdtaxa:Vedochbark": null,
    "Värdtaxa:Finarerötterochrottrådar": null,
    "ekologi": "Växer ofta i barrmattan under granar i barr- och blandskog. ",
    "Commonname": "mandelkremla",
    "matsvamp": 1,
    "total_presence": 9,
    "Artfakta": "https://artfakta.se/artinformation/taxa/5881/detaljer",
    "RL2020kat": "LC",
    "Svamp-grupp": "hattsvamp",
    "Svamp-Undersvamp-grupp": "0",
    "SIGNAL_art": "0",
    "Nyasvamp-boken": "x",
    "Giftsvamp": "0",
    "Genus": "Russula",
    "sample_plot_count": 1,
    "sample_env_count": 6,
    "Svamp-grupp-släkte": "hattsvamp",
    "images": [
      "/images/SvampBilder/Matsvampar/Russula integra-2.jpg",
      "/images/SvampBilder/Matsvampar/Russula integra-3.jpg",
      "/images/SvampBilder/Matsvampar/Russula integra-1.jpg",
      "/images/SvampBilder/Matsvampar/Russula integra-4.jpg",
      "/images/SvampBilder/Matsvampar/Russula integra-5.jpg"
    ]
  },
  {
    "SpeciesCode": "SI18-683",
    "Scientificname": "Naucoria scolecina",
    "Svampguiden": "0",
    "Kriteriedokumentation": "De skattade värdena som bedömningen baserar sig på ligger alla inom intervallet för kategorin Livskraftig (LC).",
    "OVANLIGHET": null,
    "KALKmark": null,
    "ANNANmark": null,
    "Värdtaxa:Vedochbark": null,
    "Värdtaxa:Finarerötterochrottrådar": null,
    "ekologi": null,
    "Commonname": "mörk alskräling",
    "matsvamp": 0,
    "total_presence": 4,
    "Artfakta": "https://artfakta.se/artinformation/taxa/245653/detaljer",
    "RL2020kat": "LC",
    "Svamp-grupp": "hattsvamp",
    "Svamp-Undersvamp-grupp": "0",
    "SIGNAL_art": "0",
    "Nyasvamp-boken": "0",
    "Giftsvamp": "0",
    "Genus": "Naucoria",
    "sample_plot_count": 1,
    "sample_env_count": 6,
    "Svamp-grupp-släkte": "hattsvamp",
    "images": []
  },
  {
    "SpeciesCode": "SI18-690",
    "Scientificname": "Inocybe sp.9",
    "Svampguiden": "0",
    "Kriteriedokumentation": null,
    "OVANLIGHET": null,
    "KALKmark": null,
    "ANNANmark": null,
    "Värdtaxa:Vedochbark": null,
    "Värdtaxa:Finarerötterochrottrådar": null,
    "ekologi": null,
    "Commonname": "trådskivling",
    "matsvamp": 0,
    "total_presence": 37,
    "Artfakta": "Information saknas",
    "RL2020kat": "0",
    "Svamp-grupp": "0",
    "Svamp-Undersvamp-grupp": "0",
    "SIGNAL_art": "0",
    "Nyasvamp-boken": "0",
    "Giftsvamp": "0",
    "Genus": "Inocybe",
    "sample_plot_count": 1,
    "sample_env_count": 6,
    "Svamp-grupp-släkte": "hattsvamp",
    "images": []
  },
  {
    "SpeciesCode": "SI18-702",
    "Scientificname": "Rhizopogon luteolus",
    "Svampguiden": "0",
    "Kriteriedokumentation": "De skattade värdena som bedömningen baserar sig på ligger alla inom intervallet för kategorin Livskraftig (LC).",
    "OVANLIGHET": null,
    "KALKmark": null,
    "ANNANmark": null,
    "Värdtaxa:Vedochbark": null,
    "Värdtaxa:Finarerötterochrottrådar": null,
    "ekologi": null,
    "Commonname": "gulbrun hartryffel",
    "matsvamp": 0,
    "total_presence": 1,
    "Artfakta": "https://artfakta.se/artinformation/taxa/5785/detaljer",
    "RL2020kat": "LC",
    "Svamp-grupp": "tryffel",
    "Svamp-Undersvamp-grupp": "0",
    "SIGNAL_art": "0",
    "Nyasvamp-boken": "0",
    "Giftsvamp": "0",
    "Genus": "Rhizopogon",
    "sample_plot_count": 1,
    "sample_env_count": 6,
    "Svamp-grupp-släkte": "tryffel",
    "images": []
  },
  {
    "SpeciesCode": "SI18-726",
    "Scientificname": "Inocybe aff. mixtilis sp.1",
    "Svampguiden": "0",
    "Kriteriedokumentation": null,
    "OVANLIGHET": null,
    "KALKmark": null,
    "ANNANmark": null,
    "Värdtaxa:Vedochbark": null,
    "Värdtaxa:Finarerötterochrottrådar": null,
    "ekologi": null,
    "Commonname": "löktråding",
    "matsvamp": 0,
    "total_presence": 364,
    "Artfakta": "Information saknas",
    "RL2020kat": "0",
    "Svamp-grupp": "0",
    "Svamp-Undersvamp-grupp": "0",
    "SIGNAL_art": "0",
    "Nyasvamp-boken": "0",
    "Giftsvamp": "0",
    "Genus": "Inocybe",
    "sample_plot_count": 1,
    "sample_env_count": 6,
    "Svamp-grupp-släkte": "hattsvamp",
    "images": []
  },
  {
    "SpeciesCode": "SI18-735",
    "Scientificname": "Tomentella sp.18",
    "Svampguiden": "0",
    "Kriteriedokumentation": null,
    "OVANLIGHET": null,
    "KALKmark": null,
    "ANNANmark": null,
    "Värdtaxa:Vedochbark": null,
    "Värdtaxa:Finarerötterochrottrådar": null,
    "ekologi": null,
    "Commonname": "filtskinn",
    "matsvamp": 0,
    "total_presence": 625,
    "Artfakta": "Information saknas",
    "RL2020kat": "0",
    "Svamp-grupp": "0",
    "Svamp-Undersvamp-grupp": "0",
    "SIGNAL_art": "0",
    "Nyasvamp-boken": "0",
    "Giftsvamp": "0",
    "Genus": "Tomentella",
    "sample_plot_count": 1,
    "sample_env_count": 6,
    "Svamp-grupp-släkte": "skinnsvamp",
    "images": []
  },
  {
    "SpeciesCode": "SI18-764",
    "Scientificname": "Inocybe cincinnata (coll.) sp.3",
    "Svampguiden": "0",
    "Kriteriedokumentation": "De skattade värdena som bedömningen baserar sig på ligger alla inom intervallet för kategorin Livskraftig (LC).",
    "OVANLIGHET": null,
    "KALKmark": null,
    "ANNANmark": null,
    "Värdtaxa:Vedochbark": null,
    "Värdtaxa:Finarerötterochrottrådar": "Conifers - red list assemblage",
    "ekologi": null,
    "Commonname": "violtråding",
    "matsvamp": 0,
    "total_presence": 1,
    "Artfakta": "https://artfakta.se/artinformation/taxa/4572/detaljer",
    "RL2020kat": "LC",
    "Svamp-grupp": "hattsvamp",
    "Svamp-Undersvamp-grupp": "0",
    "SIGNAL_art": "0",
    "Nyasvamp-boken": "0",
    "Giftsvamp": "0",
    "Genus": "Inocybe",
    "sample_plot_count": 1,
    "sample_env_count": 6,
    "Svamp-grupp-släkte": "hattsvamp",
    "images": []
  },
  {
    "SpeciesCode": "SI18-78",
    "Scientificname": "Cortinarius semisanguineus",
    "Svampguiden": "0",
    "Kriteriedokumentation": "De skattade värdena som bedömningen baserar sig på ligger alla inom intervallet för kategorin Livskraftig (LC).",
    "OVANLIGHET": null,
    "KALKmark": null,
    "ANNANmark": null,
    "Värdtaxa:Vedochbark": "Biota",
    "Värdtaxa:Finarerötterochrottrådar": "Biota",
    "ekologi": null,
    "Commonname": "rödskivig kanelspindling",
    "matsvamp": 0,
    "total_presence": 2,
    "Artfakta": "https://artfakta.se/artinformation/taxa/3718/detaljer",
    "RL2020kat": "LC",
    "Svamp-grupp": "hattsvamp",
    "Svamp-Undersvamp-grupp": "0",
    "SIGNAL_art": "0",
    "Nyasvamp-boken": "0",
    "Giftsvamp": "0",
    "Genus": "Cortinarius",
    "sample_plot_count": 1,
    "sample_env_count": 6,
    "Svamp-grupp-släkte": "hattsvamp",
    "images": []
  },
  {
    "SpeciesCode": "SI18-792",
    "Scientificname": "Amphinema",
    "Svampguiden": "0",
    "Kriteriedokumentation": null,
    "OVANLIGHET": null,
    "KALKmark": null,
    "ANNANmark": null,
    "Värdtaxa:Vedochbark": null,
    "Värdtaxa:Finarerötterochrottrådar": null,
    "ekologi": null,
    "Commonname": "skinnsvamp",
    "matsvamp": 0,
    "total_presence": 6,
    "Artfakta": "Information saknas",
    "RL2020kat": "0",
    "Svamp-grupp": "0",
    "Svamp-Undersvamp-grupp": "0",
    "SIGNAL_art": "0",
    "Nyasvamp-boken": "0",
    "Giftsvamp": "0",
    "Genus": "Amphinema",
    "sample_plot_count": 1,
    "sample_env_count": 6,
    "Svamp-grupp-släkte": "skinnsvamp",
    "images": []
  },
  {
    "SpeciesCode": "SI18-882",
    "Scientificname": "Polyozellus sp.5",
    "Svampguiden": "0",
    "Kriteriedokumentation": null,
    "OVANLIGHET": null,
    "KALKmark": null,
    "ANNANmark": null,
    "Värdtaxa:Vedochbark": null,
    "Värdtaxa:Finarerötterochrottrådar": null,
    "ekologi": null,
    "Commonname": "tomentelloid svamp",
    "matsvamp": 0,
    "total_presence": 16,
    "Artfakta": "Information saknas",
    "RL2020kat": "0",
    "Svamp-grupp": "0",
    "Svamp-Undersvamp-grupp": "0",
    "SIGNAL_art": "0",
    "Nyasvamp-boken": "0",
    "Giftsvamp": "0",
    "Genus": "Polyozellus",
    "sample_plot_count": 1,
    "sample_env_count": 6,
    "Svamp-grupp-släkte": "skinnsvamp",
    "images": []
  },
  {
    "SpeciesCode": "SI18-883",
    "Scientificname": "Lactarius lanceolatus",
    "Svampguiden": "0",
    "Kriteriedokumentation": "Svensk förekomst: Har inte påträffats i landet.",
    "OVANLIGHET": null,
    "KALKmark": null,
    "ANNANmark": null,
    "Värdtaxa:Vedochbark": null,
    "Värdtaxa:Finarerötterochrottrådar": "Salix",
    "ekologi": null,
    "Commonname": "riska",
    "matsvamp": 0,
    "total_presence": 68,
    "Artfakta": "https://artfakta.se/artinformation/taxa/236532/detaljer",
    "RL2020kat": "NA",
    "Svamp-grupp": "hattsvamp",
    "Svamp-Undersvamp-grupp": "0",
    "SIGNAL_art": "0",
    "Nyasvamp-boken": "0",
    "Giftsvamp": "0",
    "Genus": "Lactarius",
    "sample_plot_count": 1,
    "sample_env_count": 6,
    "Svamp-grupp-släkte": "hattsvamp",
    "images": []
  },
  {
    "SpeciesCode": "SI18-896",
    "Scientificname": "Thelephora alnii (coll.) sp.2",
    "Svampguiden": "0",
    "Kriteriedokumentation": null,
    "OVANLIGHET": null,
    "KALKmark": null,
    "ANNANmark": null,
    "Värdtaxa:Vedochbark": null,
    "Värdtaxa:Finarerötterochrottrådar": null,
    "ekologi": null,
    "Commonname": "vårtöra",
    "matsvamp": 0,
    "total_presence": 16,
    "Artfakta": "Information saknas",
    "RL2020kat": "0",
    "Svamp-grupp": "0",
    "Svamp-Undersvamp-grupp": "0",
    "SIGNAL_art": "0",
    "Nyasvamp-boken": "0",
    "Giftsvamp": "0",
    "Genus": "Thelephora",
    "sample_plot_count": 1,
    "sample_env_count": 6,
    "Svamp-grupp-släkte": "skinnsvamp",
    "images": []
  },
  {
    "SpeciesCode": "SI18-90",
    "Scientificname": "Polyozellus umbrinus",
    "Svampguiden": "0",
    "Kriteriedokumentation": "De skattade värdena som bedömningen baserar sig på ligger alla inom intervallet för kategorin Livskraftig (LC).",
    "OVANLIGHET": null,
    "KALKmark": null,
    "ANNANmark": null,
    "Värdtaxa:Vedochbark": null,
    "Värdtaxa:Finarerötterochrottrådar": "Pinus, Picea, Betula, Alnus, Salix polaris, Pyrola media, Fagus sylvatica, Dryas octopetala, Biota",
    "ekologi": null,
    "Commonname": "tomentelloid svamp",
    "matsvamp": 0,
    "total_presence": 2,
    "Artfakta": "https://artfakta.se/artinformation/taxa/6040133/detaljer",
    "RL2020kat": "LC",
    "Svamp-grupp": "skinnsvamp",
    "Svamp-Undersvamp-grupp": "0",
    "SIGNAL_art": "0",
    "Nyasvamp-boken": "0",
    "Giftsvamp": "0",
    "Genus": "Polyozellus",
    "sample_plot_count": 1,
    "sample_env_count": 6,
    "Svamp-grupp-släkte": "skinnsvamp",
    "images": []
  },
  {
    "SpeciesCode": "SI18-909",
    "Scientificname": "Tomentellopsis sp.1",
    "Svampguiden": "0",
    "Kriteriedokumentation": null,
    "OVANLIGHET": null,
    "KALKmark": null,
    "ANNANmark": null,
    "Värdtaxa:Vedochbark": null,
    "Värdtaxa:Finarerötterochrottrådar": null,
    "ekologi": null,
    "Commonname": "filtskinn",
    "matsvamp": 0,
    "total_presence": 60,
    "Artfakta": "Information saknas",
    "RL2020kat": "0",
    "Svamp-grupp": "0",
    "Svamp-Undersvamp-grupp": "0",
    "SIGNAL_art": "0",
    "Nyasvamp-boken": "0",
    "Giftsvamp": "0",
    "Genus": "Tomentellopsis",
    "sample_plot_count": 1,
    "sample_env_count": 6,
    "Svamp-grupp-släkte": "skinnsvamp",
    "images": []
  },
  {
    "SpeciesCode": "SI18-9092",
    "Scientificname": "Russula queletii",
    "Svampguiden": "0",
    "Kriteriedokumentation": "De skattade värdena som bedömningen baserar sig på ligger alla inom intervallet för kategorin Livskraftig (LC).",
    "OVANLIGHET": null,
    "KALKmark": null,
    "ANNANmark": null,
    "Värdtaxa:Vedochbark": null,
    "Värdtaxa:Finarerötterochrottrådar": null,
    "ekologi": null,
    "Commonname": "krusbärskremla",
    "matsvamp": 0,
    "total_presence": 6,
    "Artfakta": "https://artfakta.se/artinformation/taxa/5920/detaljer",
    "RL2020kat": "LC",
    "Svamp-grupp": "hattsvamp",
    "Svamp-Undersvamp-grupp": "0",
    "SIGNAL_art": "0",
    "Nyasvamp-boken": "0",
    "Giftsvamp": "0",
    "Genus": "Russula",
    "sample_plot_count": 1,
    "sample_env_count": 6,
    "Svamp-grupp-släkte": "hattsvamp",
    "images": []
  },
  {
    "SpeciesCode": "SI18-943",
    "Scientificname": "Tricholoma fulvum",
    "Svampguiden": "0",
    "Kriteriedokumentation": "De skattade värdena som bedömningen baserar sig på ligger alla inom intervallet för kategorin Livskraftig (LC).",
    "OVANLIGHET": null,
    "KALKmark": null,
    "ANNANmark": null,
    "Värdtaxa:Vedochbark": null,
    "Värdtaxa:Finarerötterochrottrådar": null,
    "ekologi": null,
    "Commonname": "fläckmusseron",
    "matsvamp": 0,
    "total_presence": 2,
    "Artfakta": "https://artfakta.se/artinformation/taxa/6269/detaljer",
    "RL2020kat": "LC",
    "Svamp-grupp": "hattsvamp",
    "Svamp-Undersvamp-grupp": "0",
    "SIGNAL_art": "0",
    "Nyasvamp-boken": "0",
    "Giftsvamp": "0",
    "Genus": "Tricholoma",
    "sample_plot_count": 1,
    "sample_env_count": 6,
    "Svamp-grupp-släkte": "hattsvamp",
    "images": [
      "/images/SvampBilder/Giftsvampar/Tricholoma fulvum-129-6269.jpg",
      "/images/SvampBilder/Giftsvampar/Tricholoma fulvum-27-6269.jpg"
    ]
  },
  {
    "SpeciesCode": "SI18-9713",
    "Scientificname": "Tomentella pilosa",
    "Svampguiden": "0",
    "Kriteriedokumentation": "De skattade värdena som bedömningen baserar sig på ligger alla inom intervallet för kategorin Livskraftig (LC).",
    "OVANLIGHET": null,
    "KALKmark": null,
    "ANNANmark": null,
    "Värdtaxa:Vedochbark": "Trivial deciduous forest trees - red list assemblage, Biota",
    "Värdtaxa:Finarerötterochrottrådar": "Biota",
    "ekologi": null,
    "Commonname": "tomentelloid svamp",
    "matsvamp": 0,
    "total_presence": 1,
    "Artfakta": "https://artfakta.se/artinformation/taxa/6174/detaljer",
    "RL2020kat": "LC",
    "Svamp-grupp": "skinnsvamp",
    "Svamp-Undersvamp-grupp": "0",
    "SIGNAL_art": "0",
    "Nyasvamp-boken": "0",
    "Giftsvamp": "0",
    "Genus": "Tomentella",
    "sample_plot_count": 1,
    "sample_env_count": 6,
    "Svamp-grupp-släkte": "skinnsvamp",
    "images": []
  },
  {
    "SpeciesCode": "SI19-3112",
    "Scientificname": "Inocybe nitidiuscula sp.1",
    "Svampguiden": "0",
    "Kriteriedokumentation": "De skattade värdena som bedömningen baserar sig på ligger alla inom intervallet för kategorin Livskraftig (LC).",
    "OVANLIGHET": null,
    "KALKmark": null,
    "ANNANmark": null,
    "Värdtaxa:Vedochbark": null,
    "Värdtaxa:Finarerötterochrottrådar": "Pinus sylvestris",
    "ekologi": null,
    "Commonname": "mosstråding",
    "matsvamp": 0,
    "total_presence": 1,
    "Artfakta": "https://artfakta.se/artinformation/taxa/4616/detaljer",
    "RL2020kat": "LC",
    "Svamp-grupp": "hattsvamp",
    "Svamp-Undersvamp-grupp": "0",
    "SIGNAL_art": "0",
    "Nyasvamp-boken": "0",
    "Giftsvamp": "0",
    "Genus": "Inocybe",
    "sample_plot_count": 1,
    "sample_env_count": 6,
    "Svamp-grupp-släkte": "hattsvamp",
    "images": []
  },
  {
    "SpeciesCode": "SI21-10258",
    "Scientificname": "Phlegmacium percome",
    "Svampguiden": "0",
    "Kriteriedokumentation": null,
    "OVANLIGHET": null,
    "KALKmark": null,
    "ANNANmark": null,
    "Värdtaxa:Vedochbark": null,
    "Värdtaxa:Finarerötterochrottrådar": null,
    "ekologi": null,
    "Commonname": "ädelspindling",
    "matsvamp": 0,
    "total_presence": 1,
    "Artfakta": "Information saknas",
    "RL2020kat": "0",
    "Svamp-grupp": "0",
    "Svamp-Undersvamp-grupp": "0",
    "SIGNAL_art": "0",
    "Nyasvamp-boken": "0",
    "Giftsvamp": "0",
    "Genus": "Phlegmacium",
    "sample_plot_count": 1,
    "sample_env_count": 6,
    "Svamp-grupp-släkte": "hattsvamp",
    "images": []
  },
  {
    "SpeciesCode": "SI21-10423",
    "Scientificname": "Inocybe nitidiuscula sp.2",
    "Svampguiden": "0",
    "Kriteriedokumentation": "De skattade värdena som bedömningen baserar sig på ligger alla inom intervallet för kategorin Livskraftig (LC).",
    "OVANLIGHET": null,
    "KALKmark": null,
    "ANNANmark": null,
    "Värdtaxa:Vedochbark": null,
    "Värdtaxa:Finarerötterochrottrådar": "Pinus sylvestris",
    "ekologi": null,
    "Commonname": "mosstråding",
    "matsvamp": 0,
    "total_presence": 4,
    "Artfakta": "https://artfakta.se/artinformation/taxa/4616/detaljer",
    "RL2020kat": "LC",
    "Svamp-grupp": "hattsvamp",
    "Svamp-Undersvamp-grupp": "0",
    "SIGNAL_art": "0",
    "Nyasvamp-boken": "0",
    "Giftsvamp": "0",
    "Genus": "Inocybe",
    "sample_plot_count": 1,
    "sample_env_count": 6,
    "Svamp-grupp-släkte": "hattsvamp",
    "images": []
  },
  {
    "SpeciesCode": "SI21-11803",
    "Scientificname": "Tomentella sp.34",
    "Svampguiden": "0",
    "Kriteriedokumentation": null,
    "OVANLIGHET": null,
    "KALKmark": null,
    "ANNANmark": null,
    "Värdtaxa:Vedochbark": null,
    "Värdtaxa:Finarerötterochrottrådar": null,
    "ekologi": null,
    "Commonname": "filtskinn",
    "matsvamp": 0,
    "total_presence": 250,
    "Artfakta": "Information saknas",
    "RL2020kat": "0",
    "Svamp-grupp": "0",
    "Svamp-Undersvamp-grupp": "0",
    "SIGNAL_art": "0",
    "Nyasvamp-boken": "0",
    "Giftsvamp": "0",
    "Genus": "Tomentella",
    "sample_plot_count": 1,
    "sample_env_count": 6,
    "Svamp-grupp-släkte": "skinnsvamp",
    "images": []
  },
  {
    "SpeciesCode": "SI21-13104",
    "Scientificname": "Pseudosperma sp.1",
    "Svampguiden": "0",
    "Kriteriedokumentation": null,
    "OVANLIGHET": null,
    "KALKmark": null,
    "ANNANmark": null,
    "Värdtaxa:Vedochbark": null,
    "Värdtaxa:Finarerötterochrottrådar": null,
    "ekologi": null,
    "Commonname": "trådskivling",
    "matsvamp": 0,
    "total_presence": 4,
    "Artfakta": "Information saknas",
    "RL2020kat": "0",
    "Svamp-grupp": "0",
    "Svamp-Undersvamp-grupp": "0",
    "SIGNAL_art": "0",
    "Nyasvamp-boken": "0",
    "Giftsvamp": "0",
    "Genus": "Pseudosperma",
    "sample_plot_count": 1,
    "sample_env_count": 6,
    "Svamp-grupp-släkte": "hattsvamp",
    "images": []
  },
  {
    "SpeciesCode": "SI21-13329",
    "Scientificname": "Hygrophorus discoideus",
    "Svampguiden": "0",
    "Kriteriedokumentation": "De skattade värdena som bedömningen baserar sig på ligger alla inom intervallet för kategorin Livskraftig (LC).",
    "OVANLIGHET": null,
    "KALKmark": null,
    "ANNANmark": null,
    "Värdtaxa:Vedochbark": null,
    "Värdtaxa:Finarerötterochrottrådar": null,
    "ekologi": null,
    "Commonname": "diskvaxskivling",
    "matsvamp": 0,
    "total_presence": 6,
    "Artfakta": "https://artfakta.se/artinformation/taxa/4405/detaljer",
    "RL2020kat": "LC",
    "Svamp-grupp": "hattsvamp",
    "Svamp-Undersvamp-grupp": "0",
    "SIGNAL_art": "0",
    "Nyasvamp-boken": "0",
    "Giftsvamp": "0",
    "Genus": "Hygrophorus",
    "sample_plot_count": 1,
    "sample_env_count": 6,
    "Svamp-grupp-släkte": "hattsvamp",
    "images": []
  },
  {
    "SpeciesCode": "SI21-13855",
    "Scientificname": "Tomentella sp.52",
    "Svampguiden": "0",
    "Kriteriedokumentation": null,
    "OVANLIGHET": null,
    "KALKmark": null,
    "ANNANmark": null,
    "Värdtaxa:Vedochbark": null,
    "Värdtaxa:Finarerötterochrottrådar": null,
    "ekologi": null,
    "Commonname": "filtskinn",
    "matsvamp": 0,
    "total_presence": 375,
    "Artfakta": "Information saknas",
    "RL2020kat": "0",
    "Svamp-grupp": "0",
    "Svamp-Undersvamp-grupp": "0",
    "SIGNAL_art": "0",
    "Nyasvamp-boken": "0",
    "Giftsvamp": "0",
    "Genus": "Tomentella",
    "sample_plot_count": 1,
    "sample_env_count": 6,
    "Svamp-grupp-släkte": "skinnsvamp",
    "images": []
  },
  {
    "SpeciesCode": "SI21-1694",
    "Scientificname": "Tomentella sp.67",
    "Svampguiden": "0",
    "Kriteriedokumentation": null,
    "OVANLIGHET": null,
    "KALKmark": null,
    "ANNANmark": null,
    "Värdtaxa:Vedochbark": null,
    "Värdtaxa:Finarerötterochrottrådar": null,
    "ekologi": null,
    "Commonname": "filtskinn",
    "matsvamp": 0,
    "total_presence": 500,
    "Artfakta": "Information saknas",
    "RL2020kat": "0",
    "Svamp-grupp": "0",
    "Svamp-Undersvamp-grupp": "0",
    "SIGNAL_art": "0",
    "Nyasvamp-boken": "0",
    "Giftsvamp": "0",
    "Genus": "Tomentella",
    "sample_plot_count": 1,
    "sample_env_count": 6,
    "Svamp-grupp-släkte": "skinnsvamp",
    "images": []
  },
  {
    "SpeciesCode": "SI21-2155",
    "Scientificname": "Serendipita vermifera (coll.) sp.4",
    "Svampguiden": "0",
    "Kriteriedokumentation": null,
    "OVANLIGHET": null,
    "KALKmark": null,
    "ANNANmark": null,
    "Värdtaxa:Vedochbark": null,
    "Värdtaxa:Finarerötterochrottrådar": null,
    "ekologi": null,
    "Commonname": "basidiesvamp",
    "matsvamp": 0,
    "total_presence": 5,
    "Artfakta": "Information saknas",
    "RL2020kat": "0",
    "Svamp-grupp": "0",
    "Svamp-Undersvamp-grupp": "0",
    "SIGNAL_art": "0",
    "Nyasvamp-boken": "0",
    "Giftsvamp": "0",
    "Genus": "Serendipita",
    "sample_plot_count": 1,
    "sample_env_count": 6,
    "Svamp-grupp-släkte": "övrigt",
    "images": []
  },
  {
    "SpeciesCode": "SI21-2868",
    "Scientificname": "Tylospora sp.2",
    "Svampguiden": "0",
    "Kriteriedokumentation": null,
    "OVANLIGHET": null,
    "KALKmark": null,
    "ANNANmark": null,
    "Värdtaxa:Vedochbark": null,
    "Värdtaxa:Finarerötterochrottrådar": null,
    "ekologi": null,
    "Commonname": "skinnsvamp",
    "matsvamp": 0,
    "total_presence": 3,
    "Artfakta": "Information saknas",
    "RL2020kat": "0",
    "Svamp-grupp": "0",
    "Svamp-Undersvamp-grupp": "0",
    "SIGNAL_art": "0",
    "Nyasvamp-boken": "0",
    "Giftsvamp": "0",
    "Genus": "Tylospora",
    "sample_plot_count": 1,
    "sample_env_count": 6,
    "Svamp-grupp-släkte": "skinnsvamp",
    "images": []
  },
  {
    "SpeciesCode": "SI21-3682",
    "Scientificname": "Tomentellopsis submollis sp.3",
    "Svampguiden": "0",
    "Kriteriedokumentation": null,
    "OVANLIGHET": null,
    "KALKmark": null,
    "ANNANmark": null,
    "Värdtaxa:Vedochbark": null,
    "Värdtaxa:Finarerötterochrottrådar": null,
    "ekologi": null,
    "Commonname": "filtskinn",
    "matsvamp": 0,
    "total_presence": 12,
    "Artfakta": "Information saknas",
    "RL2020kat": "0",
    "Svamp-grupp": "0",
    "Svamp-Undersvamp-grupp": "0",
    "SIGNAL_art": "0",
    "Nyasvamp-boken": "0",
    "Giftsvamp": "0",
    "Genus": "Tomentellopsis",
    "sample_plot_count": 1,
    "sample_env_count": 6,
    "Svamp-grupp-släkte": "skinnsvamp",
    "images": []
  },
  {
    "SpeciesCode": "SI21-3993",
    "Scientificname": "Hydnotrya bailii",
    "Svampguiden": "0",
    "Kriteriedokumentation": null,
    "OVANLIGHET": null,
    "KALKmark": null,
    "ANNANmark": null,
    "Värdtaxa:Vedochbark": null,
    "Värdtaxa:Finarerötterochrottrådar": null,
    "ekologi": null,
    "Commonname": "vecktryffel",
    "matsvamp": 0,
    "total_presence": 2,
    "Artfakta": "Information saknas",
    "RL2020kat": "0",
    "Svamp-grupp": "0",
    "Svamp-Undersvamp-grupp": "0",
    "SIGNAL_art": "0",
    "Nyasvamp-boken": "0",
    "Giftsvamp": "0",
    "Genus": "Hydnotrya",
    "sample_plot_count": 1,
    "sample_env_count": 6,
    "Svamp-grupp-släkte": "tryffel",
    "images": []
  },
  {
    "SpeciesCode": "SI21-5053",
    "Scientificname": "Sebacina sp.22",
    "Svampguiden": "0",
    "Kriteriedokumentation": null,
    "OVANLIGHET": null,
    "KALKmark": null,
    "ANNANmark": null,
    "Värdtaxa:Vedochbark": null,
    "Värdtaxa:Finarerötterochrottrådar": null,
    "ekologi": null,
    "Commonname": "talgsvamp",
    "matsvamp": 0,
    "total_presence": 29,
    "Artfakta": "Information saknas",
    "RL2020kat": "0",
    "Svamp-grupp": "0",
    "Svamp-Undersvamp-grupp": "0",
    "SIGNAL_art": "0",
    "Nyasvamp-boken": "0",
    "Giftsvamp": "0",
    "Genus": "Sebacina",
    "sample_plot_count": 1,
    "sample_env_count": 6,
    "Svamp-grupp-släkte": "övrigt",
    "images": []
  },
  {
    "SpeciesCode": "SI21-6231",
    "Scientificname": "Hyaloscypha sp.8",
    "Svampguiden": "0",
    "Kriteriedokumentation": null,
    "OVANLIGHET": null,
    "KALKmark": null,
    "ANNANmark": null,
    "Värdtaxa:Vedochbark": null,
    "Värdtaxa:Finarerötterochrottrådar": null,
    "ekologi": null,
    "Commonname": "disksvamp",
    "matsvamp": 0,
    "total_presence": 11,
    "Artfakta": "Information saknas",
    "RL2020kat": "0",
    "Svamp-grupp": "0",
    "Svamp-Undersvamp-grupp": "0",
    "SIGNAL_art": "0",
    "Nyasvamp-boken": "0",
    "Giftsvamp": "0",
    "Genus": "Hyaloscypha",
    "sample_plot_count": 1,
    "sample_env_count": 6,
    "Svamp-grupp-släkte": "skålsvamp",
    "images": []
  },
  {
    "SpeciesCode": "SI21-6254",
    "Scientificname": "Xerocomellus pruinatus sp.2",
    "Svampguiden": "0",
    "Kriteriedokumentation": "De skattade värdena som bedömningen baserar sig på ligger alla inom intervallet för kategorin Livskraftig (LC).",
    "OVANLIGHET": null,
    "KALKmark": null,
    "ANNANmark": null,
    "Värdtaxa:Vedochbark": null,
    "Värdtaxa:Finarerötterochrottrådar": null,
    "ekologi": null,
    "Commonname": "boksopp",
    "matsvamp": 0,
    "total_presence": 2,
    "Artfakta": "https://artfakta.se/artinformation/taxa/3134/detaljer",
    "RL2020kat": "LC",
    "Svamp-grupp": "sopp",
    "Svamp-Undersvamp-grupp": "0",
    "SIGNAL_art": "0",
    "Nyasvamp-boken": "0",
    "Giftsvamp": "0",
    "Genus": "Xerocomellus",
    "sample_plot_count": 1,
    "sample_env_count": 6,
    "Svamp-grupp-släkte": "sopp",
    "images": []
  },
  {
    "SpeciesCode": "SI21-9965",
    "Scientificname": "Melanogaster broomeanus sp.2",
    "Svampguiden": "0",
    "Kriteriedokumentation": "De skattade värdena som bedömningen baserar sig på ligger alla inom intervallet för kategorin Livskraftig (LC).",
    "OVANLIGHET": null,
    "KALKmark": null,
    "ANNANmark": null,
    "Värdtaxa:Vedochbark": null,
    "Värdtaxa:Finarerötterochrottrådar": null,
    "ekologi": null,
    "Commonname": "aromatisk slemtryffel",
    "matsvamp": 0,
    "total_presence": 1,
    "Artfakta": "https://artfakta.se/artinformation/taxa/5008/detaljer",
    "RL2020kat": "LC",
    "Svamp-grupp": "tryffel",
    "Svamp-Undersvamp-grupp": "0",
    "SIGNAL_art": "0",
    "Nyasvamp-boken": "0",
    "Giftsvamp": "0",
    "Genus": "Melanogaster",
    "sample_plot_count": 1,
    "sample_env_count": 6,
    "Svamp-grupp-släkte": "tryffel",
    "images": []
  }
]